README.rst
setup.py
twentyfive/__init__.py
twentyfive/cli.py
twentyfive/render.py
twentyfive.egg-info/PKG-INFO
twentyfive.egg-info/SOURCES.txt
twentyfive.egg-info/dependency_links.txt
twentyfive.egg-info/entry_points.txt
twentyfive.egg-info/requires.txt
twentyfive.egg-info/top_level.txt