Metadata-Version: 1.0
Name: twentyfive
Version: 0.2
Summary: State machine suitable for long-running systems
Home-page: http://github.com/mbr/twentyfive
Author: Marc Brinkmann
Author-email: git@marcbrinkmann.de
License: MIT
Platform: UNKNOWN
